jsonformer/__init__.py
jsonformer/format.py
jsonformer/logits_processors.py
jsonformer/main.py
jsonformer-0.11.0.dist-info/WHEEL
jsonformer-0.11.0.dist-info/METADATA
jsonformer-0.11.0.dist-info/RECORD
