Metadata-Version: 2.1
Name: jsonformer
Version: 0.11.0
Summary: 
Author: 1rgs
Author-email: rgsduke@gmail.com
Requires-Python: >=3.8,<4.0
Classifier: Programming Language :: Python :: 3
Classifier: Programming Language :: Python :: 3.8
Classifier: Programming Language :: Python :: 3.9
Classifier: Programming Language :: Python :: 3.10
Classifier: Programming Language :: Python :: 3.11
Requires-Dist: termcolor (>=2.3.0,<3.0.0)
